funner/__init__.py
funner/filefun.py
funner/packfun.py
funner/storable.py
funner/textgen.py
funner/textparse.py
funner-0.0.3.dist-info/METADATA
funner-0.0.3.dist-info/WHEEL
funner-0.0.3.dist-info/licenses/LICENSE.txt
funner-0.0.3.dist-info/RECORD
