Metadata-Version: 2.4
Name: funner
Version: 0.0.3
Summary: Collection of functions and other, including functional approach to dates (as ISO-DATE string)
Author: Nauri Nastik
License-File: LICENSE.txt
Classifier: License :: OSI Approved :: MIT License
Classifier: Operating System :: OS Independent
Classifier: Programming Language :: Python :: 3
Requires-Python: >=3.10
Requires-Dist: jinja2
Requires-Dist: loguru
Requires-Dist: pyyaml
